diffview/__init__.py
diffview/diffview.py
diffview/main.py
diffview-0.1.0.dist-info/LICENSE.md
diffview-0.1.0.dist-info/METADATA
diffview-0.1.0.dist-info/WHEEL
diffview-0.1.0.dist-info/entry_points.txt
diffview-0.1.0.dist-info/RECORD
