Metadata-Version: 2.1
Name: diffview
Version: 0.1.0
Summary: 
Author: virgilsisoe
Author-email: 28490646+sisoe24@users.noreply.github.com
Requires-Python: >=3.8,<3.11
Classifier: Programming Language :: Python :: 3
Classifier: Programming Language :: Python :: 3.8
Classifier: Programming Language :: Python :: 3.9
Classifier: Programming Language :: Python :: 3.10
Requires-Dist: pyside2 (==5.15.2.1)
